odoo/addons/website_form_require_legal/README.rst
odoo/addons/website_form_require_legal/__init__.py
odoo/addons/website_form_require_legal/__manifest__.py
odoo/addons/website_form_require_legal/i18n/de.po
odoo/addons/website_form_require_legal/i18n/es.po
odoo/addons/website_form_require_legal/i18n/it.po
odoo/addons/website_form_require_legal/i18n/website_form_require_legal.pot
odoo/addons/website_form_require_legal/readme/CONTRIBUTORS.md
odoo/addons/website_form_require_legal/readme/DESCRIPTION.md
odoo/addons/website_form_require_legal/readme/ROADMAP.md
odoo/addons/website_form_require_legal/readme/USAGE.md
odoo/addons/website_form_require_legal/static/description/icon.png
odoo/addons/website_form_require_legal/static/description/index.html
odoo/addons/website_form_require_legal/static/src/builder/form/form_options.esm.js
odoo/addons/website_form_require_legal/static/src/builder/form/form_options.xml
odoo/addons/website_form_require_legal/static/src/js/submit_button.esm.js
odoo/addons/website_form_require_legal/static/src/js/terms_and_conditions.esm.js
odoo/addons/website_form_require_legal/static/src/scss/website_form_legal.scss
odoo_addon_website_form_require_legal-19.0.1.0.1.dist-info/METADATA
odoo_addon_website_form_require_legal-19.0.1.0.1.dist-info/WHEEL
odoo_addon_website_form_require_legal-19.0.1.0.1.dist-info/top_level.txt
odoo_addon_website_form_require_legal-19.0.1.0.1.dist-info/RECORD
