Metadata-Version: 2.1
Name: odoo-addon-website_form_require_legal
Version: 19.0.1.0.1
Requires-Dist: odoo==19.0.*
Summary: Add possibility to require confirm legal terms.
Home-page: https://github.com/OCA/website
License: LGPL-3
Author: Tecnativa, Odoo Community Association (OCA)
Author-email: support@odoo-community.org
Classifier: Programming Language :: Python
Classifier: Framework :: Odoo
Classifier: Framework :: Odoo :: 19.0
Classifier: License :: OSI Approved :: GNU Lesser General Public License v3 (LGPLv3)
